django_bdtopo/__init__.py
django_bdtopo/apps/__init__.py
django_bdtopo/apps/administratif/__init__.py
django_bdtopo/apps/administratif/admin.py
django_bdtopo/apps/administratif/apps.py
django_bdtopo/apps/administratif/migrations/0001_initial.py
django_bdtopo/apps/administratif/migrations/0002_arrondissement_autorite_administrative_and_more.py
django_bdtopo/apps/administratif/migrations/__init__.py
django_bdtopo/apps/administratif/models.py
django_bdtopo/apps/administratif/views.py
django_bdtopo/apps/bati/__init__.py
django_bdtopo/apps/bati/apps.py
django_bdtopo/apps/bati/migrations/0001_initial.py
django_bdtopo/apps/bati/migrations/__init__.py
django_bdtopo/apps/bati/models.py
django_bdtopo/apps/hydrographie/__init__.py
django_bdtopo/apps/hydrographie/apps.py
django_bdtopo/apps/hydrographie/migrations/0001_initial.py
django_bdtopo/apps/hydrographie/migrations/__init__.py
django_bdtopo/apps/hydrographie/models.py
django_bdtopo/apps/lieux_nommes/__init__.py
django_bdtopo/apps/lieux_nommes/apps.py
django_bdtopo/apps/lieux_nommes/migrations/0001_initial.py
django_bdtopo/apps/lieux_nommes/migrations/__init__.py
django_bdtopo/apps/lieux_nommes/models.py
django_bdtopo/apps/occupation_du_sol/__init__.py
django_bdtopo/apps/occupation_du_sol/apps.py
django_bdtopo/apps/occupation_du_sol/migrations/0001_initial.py
django_bdtopo/apps/occupation_du_sol/migrations/__init__.py
django_bdtopo/apps/occupation_du_sol/models.py
django_bdtopo/apps/services_et_activites/__init__.py
django_bdtopo/apps/services_et_activites/admin.py
django_bdtopo/apps/services_et_activites/apps.py
django_bdtopo/apps/services_et_activites/migrations/0001_initial.py
django_bdtopo/apps/services_et_activites/migrations/__init__.py
django_bdtopo/apps/services_et_activites/models.py
django_bdtopo/apps/transport/__init__.py
django_bdtopo/apps/transport/apps.py
django_bdtopo/apps/transport/migrations/0001_initial.py
django_bdtopo/apps/transport/migrations/__init__.py
django_bdtopo/apps/transport/models.py
django_bdtopo-0.0.3.dist-info/AUTHORS.md
django_bdtopo-0.0.3.dist-info/LICENSE
django_bdtopo-0.0.3.dist-info/METADATA
django_bdtopo-0.0.3.dist-info/WHEEL
django_bdtopo-0.0.3.dist-info/RECORD
