Metadata-Version: 2.1
Name: django-bdtopo
Version: 0.0.3
Summary: Import and manage all IGN BDTOPO® data in one (customizable) app!
Home-page: https://gitlab.com/kapt/open-source/django-bdtopo
License: GPLv3
Author: Kapt dev team
Author-email: dev@kapt.mobi
Requires-Python: >=3.9,<4.0
Classifier: Environment :: Web Environment
Classifier: Framework :: Django
Classifier: Intended Audience :: Developers
Classifier: License :: OSI Approved :: GNU General Public License v3 (GPLv3)
Classifier: License :: Other/Proprietary License
Classifier: Programming Language :: Python
Classifier: Programming Language :: Python :: 3
Classifier: Programming Language :: Python :: 3.9
Classifier: Programming Language :: Python :: 3.10
Classifier: Programming Language :: Python :: 3.11
Classifier: Programming Language :: Python :: 3.12
Classifier: Topic :: Internet :: WWW/HTTP
Classifier: Topic :: Internet :: WWW/HTTP :: Dynamic Content
Requires-Dist: Django (>=4.0)
Requires-Dist: psycopg2 (>=2.9.10,<3.0.0)
Project-URL: Repository, https://gitlab.com/kapt/open-source/django-bdtopo
